{
  "window": {
    "start": "2026-06-01T09:30:00+08:00",
    "end": "2026-06-02T09:30:00+08:00",
    "timezone": "Asia/Shanghai"
  },
  "market_cap_filter": {
    "min_billion": 100.0,
    "max_billion": 2000.0,
    "description": "100-2000亿元"
  },
  "fund_flow": {
    "direction": "拥挤分化",
    "turnover_summary": "6月2日10:00附近，上证指数和深证成指偏弱，创业板指小幅翻红，科创50继续承压；前一交易日上交所成交额维持高位。",
    "main_flow_summary": "完整全A主力资金未稳定取得；用腾讯/新浪公开行情、板块涨跌、换手率和候选股票量价评分代理判断。",
    "sector_flow_summary": "有色/稀土、汽车轻量化、通信设备、部分数据中心热管理方向相对活跃；PCB/CPO等高位AI硬件分化，周期链、航空和科创权重承压。",
    "breadth_summary": "新浪行情显示早盘上涨家数多于下跌家数，但宽基指数分化，说明资金偏向低位和中小主题而非指数级扩散。",
    "data_quality": "partial"
  },
  "sector_rankings": {
    "positive": [
      {
        "rank": 1,
        "title": "新动能制造",
        "direction": "positive",
        "impact_score": 3.99,
        "magnitude": 4.0,
        "breadth": 4.2,
        "immediacy": 3.8,
        "confidence": 4.7,
        "novelty": 3.4,
        "liquidity": 3.8,
        "price_volume": 3.3
      },
      {
        "rank": 2,
        "title": "工业金属与稀土永磁",
        "direction": "positive",
        "impact_score": 3.91,
        "magnitude": 4.1,
        "breadth": 4.0,
        "immediacy": 4.0,
        "confidence": 3.8,
        "novelty": 3.4,
        "liquidity": 3.8,
        "price_volume": 3.7
      },
      {
        "rank": 3,
        "title": "创新药",
        "direction": "positive",
        "impact_score": 3.48,
        "magnitude": 3.7,
        "breadth": 3.4,
        "immediacy": 3.3,
        "confidence": 4.0,
        "novelty": 3.6,
        "liquidity": 3.0,
        "price_volume": 2.6
      },
      {
        "rank": 4,
        "title": "国资改革",
        "direction": "positive",
        "impact_score": 3.45,
        "magnitude": 3.5,
        "breadth": 3.8,
        "immediacy": 3.2,
        "confidence": 3.8,
        "novelty": 3.4,
        "liquidity": 3.4,
        "price_volume": 2.5
      },
      {
        "rank": 5,
        "title": "数据中心冷却",
        "direction": "positive",
        "impact_score": 3.38,
        "magnitude": 3.6,
        "breadth": 3.1,
        "immediacy": 3.5,
        "confidence": 3.5,
        "novelty": 3.3,
        "liquidity": 3.1,
        "price_volume": 3.2
      },
      {
        "rank": 6,
        "title": "汽车轻量化",
        "direction": "positive",
        "impact_score": 3.17,
        "magnitude": 3.3,
        "breadth": 3.0,
        "immediacy": 3.2,
        "confidence": 3.4,
        "novelty": 3.0,
        "liquidity": 3.0,
        "price_volume": 3.0
      }
    ],
    "negative": [
      {
        "rank": 1,
        "title": "高位PCB与AI硬件",
        "direction": "negative",
        "impact_score": 4.06,
        "magnitude": 4.2,
        "breadth": 4.0,
        "immediacy": 4.2,
        "confidence": 3.9,
        "novelty": 3.4,
        "liquidity": 4.4,
        "price_volume": 4.1
      },
      {
        "rank": 2,
        "title": "PMI弱需求周期链",
        "direction": "negative",
        "impact_score": 3.99,
        "magnitude": 4.0,
        "breadth": 4.3,
        "immediacy": 3.8,
        "confidence": 4.8,
        "novelty": 3.0,
        "liquidity": 3.9,
        "price_volume": 3.3
      },
      {
        "rank": 3,
        "title": "科创权重承压",
        "direction": "negative",
        "impact_score": 3.92,
        "magnitude": 4.0,
        "breadth": 3.8,
        "immediacy": 4.0,
        "confidence": 4.1,
        "novelty": 3.2,
        "liquidity": 4.1,
        "price_volume": 4.0
      },
      {
        "rank": 4,
        "title": "中小企业景气回落",
        "direction": "negative",
        "impact_score": 3.64,
        "magnitude": 3.6,
        "breadth": 3.8,
        "immediacy": 3.3,
        "confidence": 4.8,
        "novelty": 3.0,
        "liquidity": 3.2,
        "price_volume": 3.0
      },
      {
        "rank": 5,
        "title": "英伟达题材证伪",
        "direction": "negative",
        "impact_score": 3.57,
        "magnitude": 3.8,
        "breadth": 2.8,
        "immediacy": 3.6,
        "confidence": 4.0,
        "novelty": 3.3,
        "liquidity": 3.6,
        "price_volume": 3.8
      },
      {
        "rank": 6,
        "title": "航空景气偏低",
        "direction": "negative",
        "impact_score": 3.39,
        "magnitude": 3.5,
        "breadth": 2.8,
        "immediacy": 3.5,
        "confidence": 4.2,
        "novelty": 3.0,
        "liquidity": 3.1,
        "price_volume": 3.3
      }
    ]
  },
  "rankings": {
    "positive": [
      {
        "rank": 1,
        "title": "5月高技术制造业和装备制造业PMI继续扩张",
        "direction": "positive",
        "impact_score": 4.03,
        "magnitude": 4.1,
        "breadth": 4.2,
        "immediacy": 3.8,
        "confidence": 4.8,
        "novelty": 3.4,
        "liquidity": 3.8,
        "price_volume": 3.3
      },
      {
        "rank": 2,
        "title": "早盘工业金属、通信设备等热门行业相对活跃",
        "direction": "positive",
        "impact_score": 3.8,
        "magnitude": 4.0,
        "breadth": 3.8,
        "immediacy": 4.1,
        "confidence": 3.6,
        "novelty": 3.1,
        "liquidity": 3.8,
        "price_volume": 3.7
      },
      {
        "rank": 3,
        "title": "国家医保和商保创新药目录调整预期仍支撑创新药主题",
        "direction": "positive",
        "impact_score": 3.49,
        "magnitude": 3.7,
        "breadth": 3.5,
        "immediacy": 3.3,
        "confidence": 4.0,
        "novelty": 3.4,
        "liquidity": 3.1,
        "price_volume": 2.6
      },
      {
        "rank": 4,
        "title": "数据中心热管理和汽车轻量化早盘仍有结构性热度",
        "direction": "positive",
        "impact_score": 3.36,
        "magnitude": 3.5,
        "breadth": 3.2,
        "immediacy": 3.5,
        "confidence": 3.5,
        "novelty": 3.2,
        "liquidity": 3.1,
        "price_volume": 3.2
      },
      {
        "rank": 5,
        "title": "国资改革主线延续但量价确认不足",
        "direction": "positive",
        "impact_score": 3.36,
        "magnitude": 3.4,
        "breadth": 3.7,
        "immediacy": 3.1,
        "confidence": 3.7,
        "novelty": 3.3,
        "liquidity": 3.3,
        "price_volume": 2.5
      }
    ],
    "negative": [
      {
        "rank": 1,
        "title": "高位PCB与AI硬件分化，部分龙头早盘下跌",
        "direction": "negative",
        "impact_score": 4.08,
        "magnitude": 4.2,
        "breadth": 4.0,
        "immediacy": 4.2,
        "confidence": 4.0,
        "novelty": 3.4,
        "liquidity": 4.4,
        "price_volume": 4.2
      },
      {
        "rank": 2,
        "title": "制造业PMI位于临界点且新订单低于临界点",
        "direction": "negative",
        "impact_score": 4.04,
        "magnitude": 4.1,
        "breadth": 4.4,
        "immediacy": 3.8,
        "confidence": 4.8,
        "novelty": 3.0,
        "liquidity": 3.9,
        "price_volume": 3.3
      },
      {
        "rank": 3,
        "title": "科创50继续偏弱，科技权重承压",
        "direction": "negative",
        "impact_score": 3.92,
        "magnitude": 4.0,
        "breadth": 3.8,
        "immediacy": 4.0,
        "confidence": 4.1,
        "novelty": 3.2,
        "liquidity": 4.1,
        "price_volume": 4.0
      },
      {
        "rank": 4,
        "title": "中小企业PMI回落，主题扩散质量受制约",
        "direction": "negative",
        "impact_score": 3.69,
        "magnitude": 3.7,
        "breadth": 3.9,
        "immediacy": 3.3,
        "confidence": 4.8,
        "novelty": 3.0,
        "liquidity": 3.2,
        "price_volume": 3.0
      },
      {
        "rank": 5,
        "title": "英伟达相关题材证伪后的情绪拥挤仍需消化",
        "direction": "negative",
        "impact_score": 3.46,
        "magnitude": 3.6,
        "breadth": 2.7,
        "immediacy": 3.4,
        "confidence": 4.0,
        "novelty": 3.2,
        "liquidity": 3.5,
        "price_volume": 3.8
      },
      {
        "rank": 6,
        "title": "航空运输景气低于临界点，航空链继续承压",
        "direction": "negative",
        "impact_score": 3.45,
        "magnitude": 3.6,
        "breadth": 2.8,
        "immediacy": 3.5,
        "confidence": 4.4,
        "novelty": 3.0,
        "liquidity": 3.1,
        "price_volume": 3.3
      }
    ]
  },
  "stocks": [
    {
      "ticker": "000807",
      "name": "云铝股份",
      "sector": "工业金属与稀土永磁",
      "directional_role": "beneficiary",
      "market_cap_billion": 1024.09,
      "research_score": 2.86,
      "research_rating": "中性观察",
      "operation_tendency": "事件落地后再评估",
      "eligible_for_recommendation": "yes",
      "exclusion_reason": "",
      "trend_score": 3.4,
      "volume_score": 3.2,
      "retail_sentiment": 3.3,
      "retail_voc_quality_score": 3.64,
      "capital_recognition": 3.4,
      "event_alignment": 3.8,
      "risk_score": 3.0
    },
    {
      "ticker": "002126",
      "name": "银轮股份",
      "sector": "数据中心冷却",
      "directional_role": "beneficiary",
      "market_cap_billion": 423.83,
      "research_score": 2.54,
      "research_rating": "谨慎观察",
      "operation_tendency": "事件落地后再评估",
      "eligible_for_recommendation": "yes",
      "exclusion_reason": "",
      "trend_score": 3.1,
      "volume_score": 3.1,
      "retail_sentiment": 3.5,
      "retail_voc_quality_score": 3.4,
      "capital_recognition": 3.0,
      "event_alignment": 3.7,
      "risk_score": 3.5
    },
    {
      "ticker": "600019",
      "name": "宝钢股份",
      "sector": "PMI弱需求周期链",
      "directional_role": "pressure",
      "market_cap_billion": 1317.82,
      "research_score": 2.39,
      "research_rating": "谨慎观察",
      "operation_tendency": "风险回避观察",
      "eligible_for_recommendation": "yes",
      "exclusion_reason": "",
      "trend_score": 2.8,
      "volume_score": 3.0,
      "retail_sentiment": 2.8,
      "retail_voc_quality_score": 3.76,
      "capital_recognition": 2.7,
      "event_alignment": 3.8,
      "risk_score": 3.7
    },
    {
      "ticker": "002463",
      "name": "沪电股份",
      "sector": "高位PCB与AI硬件",
      "directional_role": "pressure",
      "market_cap_billion": 2350.61,
      "research_score": 2.38,
      "research_rating": "风险回避",
      "operation_tendency": "仅作风险跟踪",
      "eligible_for_recommendation": "no",
      "exclusion_reason": "市值不在100-2000亿元区间",
      "trend_score": 2.8,
      "volume_score": 3.4,
      "retail_sentiment": 4.1,
      "retail_voc_quality_score": 2.68,
      "capital_recognition": 2.8,
      "event_alignment": 3.9,
      "risk_score": 3.9
    },
    {
      "ticker": "601766",
      "name": "中国中车",
      "sector": "国资改革",
      "directional_role": "beneficiary",
      "market_cap_billion": 1658.79,
      "research_score": 2.29,
      "research_rating": "谨慎观察",
      "operation_tendency": "等待放量确认",
      "eligible_for_recommendation": "no",
      "exclusion_reason": "14日走势不足、量能确认不足、资金认可度不足",
      "trend_score": 2.4,
      "volume_score": 2.5,
      "retail_sentiment": 2.9,
      "retail_voc_quality_score": 3.88,
      "capital_recognition": 2.7,
      "event_alignment": 3.6,
      "risk_score": 3.2
    },
    {
      "ticker": "600183",
      "name": "生益科技",
      "sector": "高位PCB与AI硬件",
      "directional_role": "pressure",
      "market_cap_billion": 3189.43,
      "research_score": 2.29,
      "research_rating": "风险回避",
      "operation_tendency": "仅作风险跟踪",
      "eligible_for_recommendation": "no",
      "exclusion_reason": "市值不在100-2000亿元区间",
      "trend_score": 2.6,
      "volume_score": 3.8,
      "retail_sentiment": 4.4,
      "retail_voc_quality_score": 2.32,
      "capital_recognition": 2.6,
      "event_alignment": 4.0,
      "risk_score": 4.1
    },
    {
      "ticker": "600031",
      "name": "三一重工",
      "sector": "PMI弱需求周期链",
      "directional_role": "pressure",
      "market_cap_billion": 1639.47,
      "research_score": 2.28,
      "research_rating": "风险回避",
      "operation_tendency": "风险回避观察",
      "eligible_for_recommendation": "yes",
      "exclusion_reason": "",
      "trend_score": 2.5,
      "volume_score": 3.2,
      "retail_sentiment": 3.0,
      "retail_voc_quality_score": 4.0,
      "capital_recognition": 2.6,
      "event_alignment": 3.7,
      "risk_score": 4.0
    },
    {
      "ticker": "300476",
      "name": "胜宏科技",
      "sector": "高位PCB与AI硬件",
      "directional_role": "pressure",
      "market_cap_billion": 3323.19,
      "research_score": 2.27,
      "research_rating": "风险回避",
      "operation_tendency": "仅作风险跟踪",
      "eligible_for_recommendation": "no",
      "exclusion_reason": "市值不在100-2000亿元区间",
      "trend_score": 2.7,
      "volume_score": 3.7,
      "retail_sentiment": 4.5,
      "retail_voc_quality_score": 2.2,
      "capital_recognition": 2.6,
      "event_alignment": 4.0,
      "risk_score": 4.2
    },
    {
      "ticker": "688180",
      "name": "君实生物-U",
      "sector": "创新药",
      "directional_role": "beneficiary",
      "market_cap_billion": 331.83,
      "research_score": 2.25,
      "research_rating": "风险回避",
      "operation_tendency": "风险回避观察",
      "eligible_for_recommendation": "no",
      "exclusion_reason": "14日走势不足、资金认可度不足、综合评级为风险回避",
      "trend_score": 2.7,
      "volume_score": 3.0,
      "retail_sentiment": 3.7,
      "retail_voc_quality_score": 3.16,
      "capital_recognition": 2.7,
      "event_alignment": 3.7,
      "risk_score": 4.0
    },
    {
      "ticker": "600029",
      "name": "南方航空",
      "sector": "航空景气偏低",
      "directional_role": "pressure",
      "market_cap_billion": 967.66,
      "research_score": 2.24,
      "research_rating": "风险回避",
      "operation_tendency": "风险回避观察",
      "eligible_for_recommendation": "yes",
      "exclusion_reason": "",
      "trend_score": 2.5,
      "volume_score": 3.1,
      "retail_sentiment": 3.3,
      "retail_voc_quality_score": 3.64,
      "capital_recognition": 2.6,
      "event_alignment": 3.7,
      "risk_score": 4.0
    },
    {
      "ticker": "000636",
      "name": "风华高科",
      "sector": "英伟达题材证伪",
      "directional_role": "pressure",
      "market_cap_billion": 667.02,
      "research_score": 2.17,
      "research_rating": "风险回避",
      "operation_tendency": "风险回避观察",
      "eligible_for_recommendation": "yes",
      "exclusion_reason": "",
      "trend_score": 2.9,
      "volume_score": 4.2,
      "retail_sentiment": 4.8,
      "retail_voc_quality_score": 1.84,
      "capital_recognition": 2.1,
      "event_alignment": 4.1,
      "risk_score": 4.4
    },
    {
      "ticker": "688041",
      "name": "海光信息",
      "sector": "科创权重承压",
      "directional_role": "pressure",
      "market_cap_billion": 6473.28,
      "research_score": 2.15,
      "research_rating": "风险回避",
      "operation_tendency": "仅作风险跟踪",
      "eligible_for_recommendation": "no",
      "exclusion_reason": "市值不在100-2000亿元区间",
      "trend_score": 2.5,
      "volume_score": 3.2,
      "retail_sentiment": 4.0,
      "retail_voc_quality_score": 2.8,
      "capital_recognition": 2.5,
      "event_alignment": 3.7,
      "risk_score": 4.0
    },
    {
      "ticker": "002552",
      "name": "宝鼎科技",
      "sector": "英伟达题材证伪",
      "directional_role": "pressure",
      "market_cap_billion": 232.33,
      "research_score": 2.05,
      "research_rating": "风险回避",
      "operation_tendency": "风险回避观察",
      "eligible_for_recommendation": "yes",
      "exclusion_reason": "",
      "trend_score": 2.7,
      "volume_score": 4.0,
      "retail_sentiment": 4.8,
      "retail_voc_quality_score": 1.84,
      "capital_recognition": 2.0,
      "event_alignment": 4.0,
      "risk_score": 4.4
    }
  ],
  "eligible_beneficiaries": [
    {
      "ticker": "000807",
      "name": "云铝股份",
      "sector": "工业金属与稀土永磁",
      "directional_role": "beneficiary",
      "market_cap_billion": 1024.09,
      "research_score": 2.86,
      "research_rating": "中性观察",
      "operation_tendency": "事件落地后再评估",
      "eligible_for_recommendation": "yes",
      "exclusion_reason": "",
      "trend_score": 3.4,
      "volume_score": 3.2,
      "retail_sentiment": 3.3,
      "retail_voc_quality_score": 3.64,
      "capital_recognition": 3.4,
      "event_alignment": 3.8,
      "risk_score": 3.0
    },
    {
      "ticker": "002126",
      "name": "银轮股份",
      "sector": "数据中心冷却",
      "directional_role": "beneficiary",
      "market_cap_billion": 423.83,
      "research_score": 2.54,
      "research_rating": "谨慎观察",
      "operation_tendency": "事件落地后再评估",
      "eligible_for_recommendation": "yes",
      "exclusion_reason": "",
      "trend_score": 3.1,
      "volume_score": 3.1,
      "retail_sentiment": 3.5,
      "retail_voc_quality_score": 3.4,
      "capital_recognition": 3.0,
      "event_alignment": 3.7,
      "risk_score": 3.5
    }
  ],
  "eligible_pressure": [
    {
      "ticker": "600019",
      "name": "宝钢股份",
      "sector": "PMI弱需求周期链",
      "directional_role": "pressure",
      "market_cap_billion": 1317.82,
      "research_score": 2.39,
      "research_rating": "谨慎观察",
      "operation_tendency": "风险回避观察",
      "eligible_for_recommendation": "yes",
      "exclusion_reason": "",
      "trend_score": 2.8,
      "volume_score": 3.0,
      "retail_sentiment": 2.8,
      "retail_voc_quality_score": 3.76,
      "capital_recognition": 2.7,
      "event_alignment": 3.8,
      "risk_score": 3.7
    },
    {
      "ticker": "600031",
      "name": "三一重工",
      "sector": "PMI弱需求周期链",
      "directional_role": "pressure",
      "market_cap_billion": 1639.47,
      "research_score": 2.28,
      "research_rating": "风险回避",
      "operation_tendency": "风险回避观察",
      "eligible_for_recommendation": "yes",
      "exclusion_reason": "",
      "trend_score": 2.5,
      "volume_score": 3.2,
      "retail_sentiment": 3.0,
      "retail_voc_quality_score": 4.0,
      "capital_recognition": 2.6,
      "event_alignment": 3.7,
      "risk_score": 4.0
    },
    {
      "ticker": "600029",
      "name": "南方航空",
      "sector": "航空景气偏低",
      "directional_role": "pressure",
      "market_cap_billion": 967.66,
      "research_score": 2.24,
      "research_rating": "风险回避",
      "operation_tendency": "风险回避观察",
      "eligible_for_recommendation": "yes",
      "exclusion_reason": "",
      "trend_score": 2.5,
      "volume_score": 3.1,
      "retail_sentiment": 3.3,
      "retail_voc_quality_score": 3.64,
      "capital_recognition": 2.6,
      "event_alignment": 3.7,
      "risk_score": 4.0
    },
    {
      "ticker": "000636",
      "name": "风华高科",
      "sector": "英伟达题材证伪",
      "directional_role": "pressure",
      "market_cap_billion": 667.02,
      "research_score": 2.17,
      "research_rating": "风险回避",
      "operation_tendency": "风险回避观察",
      "eligible_for_recommendation": "yes",
      "exclusion_reason": "",
      "trend_score": 2.9,
      "volume_score": 4.2,
      "retail_sentiment": 4.8,
      "retail_voc_quality_score": 1.84,
      "capital_recognition": 2.1,
      "event_alignment": 4.1,
      "risk_score": 4.4
    },
    {
      "ticker": "002552",
      "name": "宝鼎科技",
      "sector": "英伟达题材证伪",
      "directional_role": "pressure",
      "market_cap_billion": 232.33,
      "research_score": 2.05,
      "research_rating": "风险回避",
      "operation_tendency": "风险回避观察",
      "eligible_for_recommendation": "yes",
      "exclusion_reason": "",
      "trend_score": 2.7,
      "volume_score": 4.0,
      "retail_sentiment": 4.8,
      "retail_voc_quality_score": 1.84,
      "capital_recognition": 2.0,
      "event_alignment": 4.0,
      "risk_score": 4.4
    }
  ],
  "excluded_stocks": [
    {
      "ticker": "002463",
      "name": "沪电股份",
      "sector": "高位PCB与AI硬件",
      "directional_role": "pressure",
      "market_cap_billion": 2350.61,
      "research_score": 2.38,
      "research_rating": "风险回避",
      "operation_tendency": "仅作风险跟踪",
      "eligible_for_recommendation": "no",
      "exclusion_reason": "市值不在100-2000亿元区间",
      "trend_score": 2.8,
      "volume_score": 3.4,
      "retail_sentiment": 4.1,
      "retail_voc_quality_score": 2.68,
      "capital_recognition": 2.8,
      "event_alignment": 3.9,
      "risk_score": 3.9
    },
    {
      "ticker": "601766",
      "name": "中国中车",
      "sector": "国资改革",
      "directional_role": "beneficiary",
      "market_cap_billion": 1658.79,
      "research_score": 2.29,
      "research_rating": "谨慎观察",
      "operation_tendency": "等待放量确认",
      "eligible_for_recommendation": "no",
      "exclusion_reason": "14日走势不足、量能确认不足、资金认可度不足",
      "trend_score": 2.4,
      "volume_score": 2.5,
      "retail_sentiment": 2.9,
      "retail_voc_quality_score": 3.88,
      "capital_recognition": 2.7,
      "event_alignment": 3.6,
      "risk_score": 3.2
    },
    {
      "ticker": "600183",
      "name": "生益科技",
      "sector": "高位PCB与AI硬件",
      "directional_role": "pressure",
      "market_cap_billion": 3189.43,
      "research_score": 2.29,
      "research_rating": "风险回避",
      "operation_tendency": "仅作风险跟踪",
      "eligible_for_recommendation": "no",
      "exclusion_reason": "市值不在100-2000亿元区间",
      "trend_score": 2.6,
      "volume_score": 3.8,
      "retail_sentiment": 4.4,
      "retail_voc_quality_score": 2.32,
      "capital_recognition": 2.6,
      "event_alignment": 4.0,
      "risk_score": 4.1
    },
    {
      "ticker": "300476",
      "name": "胜宏科技",
      "sector": "高位PCB与AI硬件",
      "directional_role": "pressure",
      "market_cap_billion": 3323.19,
      "research_score": 2.27,
      "research_rating": "风险回避",
      "operation_tendency": "仅作风险跟踪",
      "eligible_for_recommendation": "no",
      "exclusion_reason": "市值不在100-2000亿元区间",
      "trend_score": 2.7,
      "volume_score": 3.7,
      "retail_sentiment": 4.5,
      "retail_voc_quality_score": 2.2,
      "capital_recognition": 2.6,
      "event_alignment": 4.0,
      "risk_score": 4.2
    },
    {
      "ticker": "688180",
      "name": "君实生物-U",
      "sector": "创新药",
      "directional_role": "beneficiary",
      "market_cap_billion": 331.83,
      "research_score": 2.25,
      "research_rating": "风险回避",
      "operation_tendency": "风险回避观察",
      "eligible_for_recommendation": "no",
      "exclusion_reason": "14日走势不足、资金认可度不足、综合评级为风险回避",
      "trend_score": 2.7,
      "volume_score": 3.0,
      "retail_sentiment": 3.7,
      "retail_voc_quality_score": 3.16,
      "capital_recognition": 2.7,
      "event_alignment": 3.7,
      "risk_score": 4.0
    },
    {
      "ticker": "688041",
      "name": "海光信息",
      "sector": "科创权重承压",
      "directional_role": "pressure",
      "market_cap_billion": 6473.28,
      "research_score": 2.15,
      "research_rating": "风险回避",
      "operation_tendency": "仅作风险跟踪",
      "eligible_for_recommendation": "no",
      "exclusion_reason": "市值不在100-2000亿元区间",
      "trend_score": 2.5,
      "volume_score": 3.2,
      "retail_sentiment": 4.0,
      "retail_voc_quality_score": 2.8,
      "capital_recognition": 2.5,
      "event_alignment": 3.7,
      "risk_score": 4.0
    }
  ],
  "warnings": [
    "Fund-flow data quality is `partial`; lower confidence in market-direction judgment.",
    "Only 5 positive candidates available; positive Top 10 is incomplete.",
    "Only 6 negative candidates available; negative Top 10 is incomplete.",
    "akshare已安装但当前探测抓取被远端断开，个股市值降级使用腾讯无密钥公开行情补全。",
    "Sina/Tencent公开报价可用；Eastmoney当前返回空响应；iTick未配置免费token；Zhitu仅demo可用；baostock未安装。",
    "散户VOC使用公开行情页热度、涨跌幅、换手率和异常波动代理，未使用个人级数据。",
    "未稳定获取完整全A主力净流入、北向资金和逐日14交易日K线；量价使用公开行情、成交额和脚本评分近似。"
  ]
}
